zkpytb/__init__.py
zkpytb/dicts.py
zkpytb/json.py
zkpytb/logging.py
zkpytb/pandas.py
zkpytb/priorityqueue.py
zkpytb/utils.py
zkpytb-0.3.0.dist-info/LICENSE
zkpytb-0.3.0.dist-info/METADATA
zkpytb-0.3.0.dist-info/WHEEL
zkpytb-0.3.0.dist-info/top_level.txt
zkpytb-0.3.0.dist-info/RECORD
