Metadata-Version: 2.1
Name: zkpytb
Version: 0.3.0
Summary: A collection of useful functions by Zertrin
Home-page: https://github.com/zertrin/zkpytb
Author: Marc Gallet
Author-email: zertrin@gmail.com
License: MIT license
Project-URL: Documentation, https://zkpytb.readthedocs.io/
Project-URL: Say Thanks!, https://saythanks.io/to/zertrin
Project-URL: Source, https://github.com/zertrin/zkpytb
Project-URL: Tracker, https://github.com/zertrin/zkpytb/issues
Keywords: zkpytb
Classifier: Development Status :: 2 - Pre-Alpha
Classifier: Intended Audience :: Developers
Classifier: License :: OSI Approved :: MIT License
Classifier: Natural Language :: English
Classifier: Programming Language :: Python :: 3
Classifier: Programming Language :: Python :: 3.7
Classifier: Programming Language :: Python :: 3.8
Classifier: Programming Language :: Python :: 3.9
Classifier: Programming Language :: Python :: 3.10
Classifier: Programming Language :: Python :: 3.11
Classifier: Programming Language :: Python :: 3.12
Requires-Python: >=3.7, <4
License-File: LICENSE
